mcp_weather_http_lxy4633/__init__.py
mcp_weather_http_lxy4633/__main__.py
mcp_weather_http_lxy4633/server.py
mcp_weather_http_lxy4633-1.1.0.dist-info/METADATA
mcp_weather_http_lxy4633-1.1.0.dist-info/WHEEL
mcp_weather_http_lxy4633-1.1.0.dist-info/entry_points.txt
mcp_weather_http_lxy4633-1.1.0.dist-info/top_level.txt
mcp_weather_http_lxy4633-1.1.0.dist-info/RECORD
